MANIFEST.in
README.md
package_info.json
requirements.txt
setup.py
pytest_th2_bdd.egg-info/PKG-INFO
pytest_th2_bdd.egg-info/SOURCES.txt
pytest_th2_bdd.egg-info/dependency_links.txt
pytest_th2_bdd.egg-info/entry_points.txt
pytest_th2_bdd.egg-info/requires.txt
pytest_th2_bdd.egg-info/top_level.txt
th2_bdd/__init__.py
th2_bdd/pytest/__init__.py
th2_bdd/table/__init__.py
th2_bdd/util/__init__.py
th2_bdd/util/sf.py