Metadata-Version: 2.1
Name: pytest-th2-bdd
Version: 0.0.1.dev2320248668
Summary: pytest_th2_bdd
Home-page: UNKNOWN
Author: TH2-devs
Author-email: th2-devs@exactprosystems.com
License: Apache License 2.0
Platform: UNKNOWN
Classifier: Framework :: Pytest
Requires-Python: >=3.7
